jl_serverless/__init__.py
jl_serverless/cli.py
jl_serverless-0.1.1.dist-info/METADATA
jl_serverless-0.1.1.dist-info/WHEEL
jl_serverless-0.1.1.dist-info/entry_points.txt
jl_serverless-0.1.1.dist-info/top_level.txt
jl_serverless-0.1.1.dist-info/RECORD
