Metadata-Version: 2.1
Name: jl-serverless
Version: 0.1.1
Summary: A CLI tool to run scripts on a remote server.
Home-page: https://github.com/Arunkumar-Dhanraj/JL-Serverless.git
Author: Arunkumar
Author-email: arun19ict@gmail.com
Classifier: Programming Language :: Python :: 3
Classifier: License :: OSI Approved :: MIT License
Classifier: Operating System :: OS Independent
Requires-Dist: click
Requires-Dist: requests
